setup.py
pynasdaq/__init__.py
pynasdaq/common.py
pynasdaq/dividend.py
pynasdaq/press.py
pynasdaq/stock.py
pynasdaq.egg-info/PKG-INFO
pynasdaq.egg-info/SOURCES.txt
pynasdaq.egg-info/dependency_links.txt
pynasdaq.egg-info/not-zip-safe
pynasdaq.egg-info/requires.txt
pynasdaq.egg-info/top_level.txt