Metadata-Version: 2.1
Name: pynasdaq
Version: 0.4.0
Summary: Retrieve NASDAQ stock and dividend data
Home-page: https://github.com/makkader/pynasdaq
Author: Mak Kader
Author-email: abdul.kader880@gmail.com
License: MIT
Platform: UNKNOWN
